bcells/__init__.py
bcells/data/__init__.py
bcells/data/fetchers.py
bcells/data/traces_bg_0muM_subset.pkl
bcells/data/traces_bg_1000muM_subset.pkl
bcells/data/traces_bg_10muM_subset.pkl
bcells/processing/__init__.py
bcells/processing/characteristic_func.py
bcells/processing/data_manipulation.py
bcells/processing/pipeline.py
bcells/processing/plotting.py
bcells/processing/probability_func.py
bcells/processing/process.py
bcells/processing/standardization.py
bcells/processing/wasserstein.py
bcells/segmentation/__init__.py
bcells/segmentation/extract.py
bcells/segmentation/imaging.py
bcells/segmentation/segment.py
bcells/uni/__init__.py
bcells/uni/unimodalize.py
bcells/util/__init__.py
bcells/util/load.py
bcells/util/storing.py
bcells-1.0.3.dist-info/METADATA
bcells-1.0.3.dist-info/WHEEL
bcells-1.0.3.dist-info/licenses/LICENSE.txt
bcells-1.0.3.dist-info/RECORD
