Metadata-Version: 2.1
Name: bcells
Version: 1.0.3
Summary: Analysis of videos of cells with respect to their change in brightness over time.
Project-URL: Repository, https://gitlab.gwdg.de/torben.maass/bcells
Author: Housen Li
Author-email: Torben Maaß <torben.maass@stud.uni-goettingen.de>
License:                     GNU GENERAL PUBLIC LICENSE
License-File: LICENSE.txt
Keywords: cell
Classifier: Operating System :: OS Independent
Classifier: Programming Language :: Python
Requires-Python: >=3.10
Requires-Dist: bm3d
Requires-Dist: cvxopt
Requires-Dist: matplotlib
Requires-Dist: nd2
Requires-Dist: numpy
Requires-Dist: pandas
Requires-Dist: scikit-image
Requires-Dist: scipy
Requires-Dist: seaborn
